setup.cfg
setup.py
bin/j2s
j2s/__init__.py
j2s/__main__.py
j2s.egg-info/PKG-INFO
j2s.egg-info/SOURCES.txt
j2s.egg-info/dependency_links.txt
j2s.egg-info/top_level.txt