Metadata-Version: 1.0
Name: j2s
Version: 1.0.1
Summary: convert a json dictionary to a swagger definition
Home-page: https://github.com/af-inet/j2s
Author: David Hargat
Author-email: davidmhargat@gmail.com
License: MIT
Keywords: json to swagger
Platform: UNKNOWN
